appsync_subscription_manager/__init__.py
appsync_subscription_manager/exceptions.py
appsync_subscription_manager/types.py
epiphani_appsync_subscription_manager-0.1.3.dist-info/LICENSE
epiphani_appsync_subscription_manager-0.1.3.dist-info/METADATA
epiphani_appsync_subscription_manager-0.1.3.dist-info/WHEEL
epiphani_appsync_subscription_manager-0.1.3.dist-info/top_level.txt
epiphani_appsync_subscription_manager-0.1.3.dist-info/RECORD
