Metadata-Version: 2.1
Name: epiphani-appsync-subscription-manager
Version: 0.1.3
Summary: python client for managing AWS appsync graphql subscriptions
Home-page: https://github.com/epiphani-inc/appsync-subscription-manager
Author: Praveen Madhav
Author-email: praveen@epiphani.io
License: MIT
Platform: UNKNOWN
Requires-Python: >=2.7
Requires-Dist: future
Requires-Dist: six
Requires-Dist: warrant (>=0.6.1)
Requires-Dist: websocket-client (>=0.57.0)
Requires-Dist: enum34 ; python_version < "3.4"
